fabric_quick_setup/__init__.py
fabric_quick_setup/cli.py
fabric_quick_setup/mod.py
fabric_quick_setup/test.py
fabric_quick_setup-0.2.4.dist-info/LICENSE
fabric_quick_setup-0.2.4.dist-info/METADATA
fabric_quick_setup-0.2.4.dist-info/WHEEL
fabric_quick_setup-0.2.4.dist-info/entry_points.txt
fabric_quick_setup-0.2.4.dist-info/top_level.txt
fabric_quick_setup-0.2.4.dist-info/RECORD
