Metadata-Version: 2.1
Name: fabric-quick-setup
Version: 0.2.4
Summary: CLI to quickly and easily install Fabric Loader and Popular Minecraft Mods
Home-page: http://github.com/max-niederman/fabric-quick-setup
Author: Max Niederman
Author-email: maxniederman@gmail.com
License: MIT
Platform: UNKNOWN
Classifier: Development Status :: 3 - Alpha
Classifier: License :: OSI Approved :: MIT License
Classifier: Programming Language :: Python :: 3
Requires-Dist: lxml
Requires-Dist: termcolor
Requires-Dist: colorama
